{"nodes": [{"id": "app_src_test_kotlin_com_x8bit_bitwarden_data_vault_datasource_disk_dao_fakedomainsdao_kt", "label": "FakeDomainsDao.kt", "file_type": "code", "source_file": "app\\src\\test\\kotlin\\com\\x8bit\\bitwarden\\data\\vault\\datasource\\disk\\dao\\FakeDomainsDao.kt", "source_location": "L1"}, {"id": "fakedomainsdao_fakedomainsdao", "label": "FakeDomainsDao", "file_type": "code", "source_file": "app\\src\\test\\kotlin\\com\\x8bit\\bitwarden\\data\\vault\\datasource\\disk\\dao\\FakeDomainsDao.kt", "source_location": "L7"}, {"id": "fakedomainsdao_fakedomainsdao_deletedomains", "label": ".deleteDomains()", "file_type": "code", "source_file": "app\\src\\test\\kotlin\\com\\x8bit\\bitwarden\\data\\vault\\datasource\\disk\\dao\\FakeDomainsDao.kt", "source_location": "L16"}, {"id": "fakedomainsdao_fakedomainsdao_getdomainsflow", "label": ".getDomainsFlow()", "file_type": "code", "source_file": "app\\src\\test\\kotlin\\com\\x8bit\\bitwarden\\data\\vault\\datasource\\disk\\dao\\FakeDomainsDao.kt", "source_location": "L20"}, {"id": "fakedomainsdao_fakedomainsdao_insertdomains", "label": ".insertDomains()", "file_type": "code", "source_file": "app\\src\\test\\kotlin\\com\\x8bit\\bitwarden\\data\\vault\\datasource\\disk\\dao\\FakeDomainsDao.kt", "source_location": "L25"}], "edges": [{"source": "app_src_test_kotlin_com_x8bit_bitwarden_data_vault_datasource_disk_dao_fakedomainsdao_kt", "target": "fakedomainsdao_fakedomainsdao", "relation": "contains", "confidence": "EXTRACTED", "source_file": "app\\src\\test\\kotlin\\com\\x8bit\\bitwarden\\data\\vault\\datasource\\disk\\dao\\FakeDomainsDao.kt", "source_location": "L7", "weight": 1.0}, {"source": "fakedomainsdao_fakedomainsdao", "target": "fakedomainsdao_fakedomainsdao_deletedomains", "relation": "method", "confidence": "EXTRACTED", "source_file": "app\\src\\test\\kotlin\\com\\x8bit\\bitwarden\\data\\vault\\datasource\\disk\\dao\\FakeDomainsDao.kt", "source_location": "L16", "weight": 1.0}, {"source": "fakedomainsdao_fakedomainsdao", "target": "fakedomainsdao_fakedomainsdao_getdomainsflow", "relation": "method", "confidence": "EXTRACTED", "source_file": "app\\src\\test\\kotlin\\com\\x8bit\\bitwarden\\data\\vault\\datasource\\disk\\dao\\FakeDomainsDao.kt", "source_location": "L20", "weight": 1.0}, {"source": "fakedomainsdao_fakedomainsdao", "target": "fakedomainsdao_fakedomainsdao_insertdomains", "relation": "method", "confidence": "EXTRACTED", "source_file": "app\\src\\test\\kotlin\\com\\x8bit\\bitwarden\\data\\vault\\datasource\\disk\\dao\\FakeDomainsDao.kt", "source_location": "L25", "weight": 1.0}], "raw_calls": []}