{"nodes": [{"id": "data_src_main_kotlin_com_bitwarden_data_manager_flightrecorder_flightrecordermanager_kt", "label": "FlightRecorderManager.kt", "file_type": "code", "source_file": "data\\src\\main\\kotlin\\com\\bitwarden\\data\\manager\\flightrecorder\\FlightRecorderManager.kt", "source_location": "L1"}, {"id": "flightrecordermanager_flightrecordermanager", "label": "FlightRecorderManager", "file_type": "code", "source_file": "data\\src\\main\\kotlin\\com\\bitwarden\\data\\manager\\flightrecorder\\FlightRecorderManager.kt", "source_location": "L10"}, {"id": "flightrecordermanager_flightrecordermanager_dismissflightrecorderbanner", "label": ".dismissFlightRecorderBanner()", "file_type": "code", "source_file": "data\\src\\main\\kotlin\\com\\bitwarden\\data\\manager\\flightrecorder\\FlightRecorderManager.kt", "source_location": "L24"}, {"id": "flightrecordermanager_flightrecordermanager_startflightrecorder", "label": ".startFlightRecorder()", "file_type": "code", "source_file": "data\\src\\main\\kotlin\\com\\bitwarden\\data\\manager\\flightrecorder\\FlightRecorderManager.kt", "source_location": "L29"}, {"id": "flightrecordermanager_flightrecordermanager_endflightrecorder", "label": ".endFlightRecorder()", "file_type": "code", "source_file": "data\\src\\main\\kotlin\\com\\bitwarden\\data\\manager\\flightrecorder\\FlightRecorderManager.kt", "source_location": "L34"}, {"id": "flightrecordermanager_flightrecordermanager_deletelog", "label": ".deleteLog()", "file_type": "code", "source_file": "data\\src\\main\\kotlin\\com\\bitwarden\\data\\manager\\flightrecorder\\FlightRecorderManager.kt", "source_location": "L39"}, {"id": "flightrecordermanager_flightrecordermanager_deletealllogs", "label": ".deleteAllLogs()", "file_type": "code", "source_file": "data\\src\\main\\kotlin\\com\\bitwarden\\data\\manager\\flightrecorder\\FlightRecorderManager.kt", "source_location": "L44"}], "edges": [{"source": "data_src_main_kotlin_com_bitwarden_data_manager_flightrecorder_flightrecordermanager_kt", "target": "flightrecordermanager_flightrecordermanager", "relation": "contains", "confidence": "EXTRACTED", "source_file": "data\\src\\main\\kotlin\\com\\bitwarden\\data\\manager\\flightrecorder\\FlightRecorderManager.kt", "source_location": "L10", "weight": 1.0}, {"source": "flightrecordermanager_flightrecordermanager", "target": "flightrecordermanager_flightrecordermanager_dismissflightrecorderbanner", "relation": "method", "confidence": "EXTRACTED", "source_file": "data\\src\\main\\kotlin\\com\\bitwarden\\data\\manager\\flightrecorder\\FlightRecorderManager.kt", "source_location": "L24", "weight": 1.0}, {"source": "flightrecordermanager_flightrecordermanager", "target": "flightrecordermanager_flightrecordermanager_startflightrecorder", "relation": "method", "confidence": "EXTRACTED", "source_file": "data\\src\\main\\kotlin\\com\\bitwarden\\data\\manager\\flightrecorder\\FlightRecorderManager.kt", "source_location": "L29", "weight": 1.0}, {"source": "flightrecordermanager_flightrecordermanager", "target": "flightrecordermanager_flightrecordermanager_endflightrecorder", "relation": "method", "confidence": "EXTRACTED", "source_file": "data\\src\\main\\kotlin\\com\\bitwarden\\data\\manager\\flightrecorder\\FlightRecorderManager.kt", "source_location": "L34", "weight": 1.0}, {"source": "flightrecordermanager_flightrecordermanager", "target": "flightrecordermanager_flightrecordermanager_deletelog", "relation": "method", "confidence": "EXTRACTED", "source_file": "data\\src\\main\\kotlin\\com\\bitwarden\\data\\manager\\flightrecorder\\FlightRecorderManager.kt", "source_location": "L39", "weight": 1.0}, {"source": "flightrecordermanager_flightrecordermanager", "target": "flightrecordermanager_flightrecordermanager_deletealllogs", "relation": "method", "confidence": "EXTRACTED", "source_file": "data\\src\\main\\kotlin\\com\\bitwarden\\data\\manager\\flightrecorder\\FlightRecorderManager.kt", "source_location": "L44", "weight": 1.0}], "raw_calls": []}