{"nodes": [{"id": "app_src_main_kotlin_com_x8bit_bitwarden_ui_vault_feature_vault_model_vaultfiltertype_kt", "label": "VaultFilterType.kt", "file_type": "code", "source_file": "app\\src\\main\\kotlin\\com\\x8bit\\bitwarden\\ui\\vault\\feature\\vault\\model\\VaultFilterType.kt", "source_location": "L1"}, {"id": "vaultfiltertype_vaultfiltertype", "label": "VaultFilterType", "file_type": "code", "source_file": "app\\src\\main\\kotlin\\com\\x8bit\\bitwarden\\ui\\vault\\feature\\vault\\model\\VaultFilterType.kt", "source_location": "L12"}, {"id": "vaultfiltertype_allvaults", "label": "AllVaults", "file_type": "code", "source_file": "app\\src\\main\\kotlin\\com\\x8bit\\bitwarden\\ui\\vault\\feature\\vault\\model\\VaultFilterType.kt", "source_location": "L27"}, {"id": "vaultfiltertype_myvault", "label": "MyVault", "file_type": "code", "source_file": "app\\src\\main\\kotlin\\com\\x8bit\\bitwarden\\ui\\vault\\feature\\vault\\model\\VaultFilterType.kt", "source_location": "L36"}, {"id": "vaultfiltertype_organizationvault", "label": "OrganizationVault", "file_type": "code", "source_file": "app\\src\\main\\kotlin\\com\\x8bit\\bitwarden\\ui\\vault\\feature\\vault\\model\\VaultFilterType.kt", "source_location": "L45"}], "edges": [{"source": "app_src_main_kotlin_com_x8bit_bitwarden_ui_vault_feature_vault_model_vaultfiltertype_kt", "target": "vaultfiltertype_vaultfiltertype", "relation": "contains", "confidence": "EXTRACTED", "source_file": "app\\src\\main\\kotlin\\com\\x8bit\\bitwarden\\ui\\vault\\feature\\vault\\model\\VaultFilterType.kt", "source_location": "L12", "weight": 1.0}, {"source": "app_src_main_kotlin_com_x8bit_bitwarden_ui_vault_feature_vault_model_vaultfiltertype_kt", "target": "vaultfiltertype_allvaults", "relation": "contains", "confidence": "EXTRACTED", "source_file": "app\\src\\main\\kotlin\\com\\x8bit\\bitwarden\\ui\\vault\\feature\\vault\\model\\VaultFilterType.kt", "source_location": "L27", "weight": 1.0}, {"source": "app_src_main_kotlin_com_x8bit_bitwarden_ui_vault_feature_vault_model_vaultfiltertype_kt", "target": "vaultfiltertype_myvault", "relation": "contains", "confidence": "EXTRACTED", "source_file": "app\\src\\main\\kotlin\\com\\x8bit\\bitwarden\\ui\\vault\\feature\\vault\\model\\VaultFilterType.kt", "source_location": "L36", "weight": 1.0}, {"source": "app_src_main_kotlin_com_x8bit_bitwarden_ui_vault_feature_vault_model_vaultfiltertype_kt", "target": "vaultfiltertype_organizationvault", "relation": "contains", "confidence": "EXTRACTED", "source_file": "app\\src\\main\\kotlin\\com\\x8bit\\bitwarden\\ui\\vault\\feature\\vault\\model\\VaultFilterType.kt", "source_location": "L45", "weight": 1.0}], "raw_calls": []}