{"nodes": [{"id": "ui_src_main_kotlin_com_bitwarden_ui_platform_feature_cardscanner_util_cardscanresult_kt", "label": "CardScanResult.kt", "file_type": "code", "source_file": "ui\\src\\main\\kotlin\\com\\bitwarden\\ui\\platform\\feature\\cardscanner\\util\\CardScanResult.kt", "source_location": "L1"}, {"id": "cardscanresult_cardscanresult", "label": "CardScanResult", "file_type": "code", "source_file": "ui\\src\\main\\kotlin\\com\\bitwarden\\ui\\platform\\feature\\cardscanner\\util\\CardScanResult.kt", "source_location": "L6"}, {"id": "cardscanresult_success", "label": "Success", "file_type": "code", "source_file": "ui\\src\\main\\kotlin\\com\\bitwarden\\ui\\platform\\feature\\cardscanner\\util\\CardScanResult.kt", "source_location": "L13"}, {"id": "cardscanresult_scanerror", "label": "ScanError", "file_type": "code", "source_file": "ui\\src\\main\\kotlin\\com\\bitwarden\\ui\\platform\\feature\\cardscanner\\util\\CardScanResult.kt", "source_location": "L18"}], "edges": [{"source": "ui_src_main_kotlin_com_bitwarden_ui_platform_feature_cardscanner_util_cardscanresult_kt", "target": "cardscanresult_cardscanresult", "relation": "contains", "confidence": "EXTRACTED", "source_file": "ui\\src\\main\\kotlin\\com\\bitwarden\\ui\\platform\\feature\\cardscanner\\util\\CardScanResult.kt", "source_location": "L6", "weight": 1.0}, {"source": "ui_src_main_kotlin_com_bitwarden_ui_platform_feature_cardscanner_util_cardscanresult_kt", "target": "cardscanresult_success", "relation": "contains", "confidence": "EXTRACTED", "source_file": "ui\\src\\main\\kotlin\\com\\bitwarden\\ui\\platform\\feature\\cardscanner\\util\\CardScanResult.kt", "source_location": "L13", "weight": 1.0}, {"source": "ui_src_main_kotlin_com_bitwarden_ui_platform_feature_cardscanner_util_cardscanresult_kt", "target": "cardscanresult_scanerror", "relation": "contains", "confidence": "EXTRACTED", "source_file": "ui\\src\\main\\kotlin\\com\\bitwarden\\ui\\platform\\feature\\cardscanner\\util\\CardScanResult.kt", "source_location": "L18", "weight": 1.0}], "raw_calls": []}