{"nodes": [{"id": "app_src_main_kotlin_com_x8bit_bitwarden_data_tools_generator_datasource_disk_generatordisksourceimpl_kt", "label": "GeneratorDiskSourceImpl.kt", "file_type": "code", "source_file": "app\\src\\main\\kotlin\\com\\x8bit\\bitwarden\\data\\tools\\generator\\datasource\\disk\\GeneratorDiskSourceImpl.kt", "source_location": "L1"}, {"id": "generatordisksourceimpl_generatordisksourceimpl", "label": "GeneratorDiskSourceImpl", "file_type": "code", "source_file": "app\\src\\main\\kotlin\\com\\x8bit\\bitwarden\\data\\tools\\generator\\datasource\\disk\\GeneratorDiskSourceImpl.kt", "source_location": "L16"}, {"id": "generatordisksourceimpl_generatordisksourceimpl_cleardata", "label": ".clearData()", "file_type": "code", "source_file": "app\\src\\main\\kotlin\\com\\x8bit\\bitwarden\\data\\tools\\generator\\datasource\\disk\\GeneratorDiskSourceImpl.kt", "source_location": "L22"}, {"id": "generatordisksourceimpl_generatordisksourceimpl_getpasscodegenerationoptions", "label": ".getPasscodeGenerationOptions()", "file_type": "code", "source_file": "app\\src\\main\\kotlin\\com\\x8bit\\bitwarden\\data\\tools\\generator\\datasource\\disk\\GeneratorDiskSourceImpl.kt", "source_location": "L27"}, {"id": "generatordisksourceimpl_generatordisksourceimpl_storepasscodegenerationoptions", "label": ".storePasscodeGenerationOptions()", "file_type": "code", "source_file": "app\\src\\main\\kotlin\\com\\x8bit\\bitwarden\\data\\tools\\generator\\datasource\\disk\\GeneratorDiskSourceImpl.kt", "source_location": "L31"}, {"id": "generatordisksourceimpl_generatordisksourceimpl_getusernamegenerationoptions", "label": ".getUsernameGenerationOptions()", "file_type": "code", "source_file": "app\\src\\main\\kotlin\\com\\x8bit\\bitwarden\\data\\tools\\generator\\datasource\\disk\\GeneratorDiskSourceImpl.kt", "source_location": "L41"}, {"id": "generatordisksourceimpl_generatordisksourceimpl_storeusernamegenerationoptions", "label": ".storeUsernameGenerationOptions()", "file_type": "code", "source_file": "app\\src\\main\\kotlin\\com\\x8bit\\bitwarden\\data\\tools\\generator\\datasource\\disk\\GeneratorDiskSourceImpl.kt", "source_location": "L45"}], "edges": [{"source": "app_src_main_kotlin_com_x8bit_bitwarden_data_tools_generator_datasource_disk_generatordisksourceimpl_kt", "target": "generatordisksourceimpl_generatordisksourceimpl", "relation": "contains", "confidence": "EXTRACTED", "source_file": "app\\src\\main\\kotlin\\com\\x8bit\\bitwarden\\data\\tools\\generator\\datasource\\disk\\GeneratorDiskSourceImpl.kt", "source_location": "L16", "weight": 1.0}, {"source": "generatordisksourceimpl_generatordisksourceimpl", "target": "generatordisksourceimpl_generatordisksourceimpl_cleardata", "relation": "method", "confidence": "EXTRACTED", "source_file": "app\\src\\main\\kotlin\\com\\x8bit\\bitwarden\\data\\tools\\generator\\datasource\\disk\\GeneratorDiskSourceImpl.kt", "source_location": "L22", "weight": 1.0}, {"source": "generatordisksourceimpl_generatordisksourceimpl", "target": "generatordisksourceimpl_generatordisksourceimpl_getpasscodegenerationoptions", "relation": "method", "confidence": "EXTRACTED", "source_file": "app\\src\\main\\kotlin\\com\\x8bit\\bitwarden\\data\\tools\\generator\\datasource\\disk\\GeneratorDiskSourceImpl.kt", "source_location": "L27", "weight": 1.0}, {"source": "generatordisksourceimpl_generatordisksourceimpl", "target": "generatordisksourceimpl_generatordisksourceimpl_storepasscodegenerationoptions", "relation": "method", "confidence": "EXTRACTED", "source_file": "app\\src\\main\\kotlin\\com\\x8bit\\bitwarden\\data\\tools\\generator\\datasource\\disk\\GeneratorDiskSourceImpl.kt", "source_location": "L31", "weight": 1.0}, {"source": "generatordisksourceimpl_generatordisksourceimpl", "target": "generatordisksourceimpl_generatordisksourceimpl_getusernamegenerationoptions", "relation": "method", "confidence": "EXTRACTED", "source_file": "app\\src\\main\\kotlin\\com\\x8bit\\bitwarden\\data\\tools\\generator\\datasource\\disk\\GeneratorDiskSourceImpl.kt", "source_location": "L41", "weight": 1.0}, {"source": "generatordisksourceimpl_generatordisksourceimpl", "target": "generatordisksourceimpl_generatordisksourceimpl_storeusernamegenerationoptions", "relation": "method", "confidence": "EXTRACTED", "source_file": "app\\src\\main\\kotlin\\com\\x8bit\\bitwarden\\data\\tools\\generator\\datasource\\disk\\GeneratorDiskSourceImpl.kt", "source_location": "L45", "weight": 1.0}], "raw_calls": []}