{"nodes": [{"id": "authenticator_src_main_kotlin_com_bitwarden_authenticator_data_platform_manager_lock_model_applockstate_kt", "label": "AppLockState.kt", "file_type": "code", "source_file": "authenticator\\src\\main\\kotlin\\com\\bitwarden\\authenticator\\data\\platform\\manager\\lock\\model\\AppLockState.kt", "source_location": "L1"}, {"id": "applockstate_applockstate", "label": "AppLockState", "file_type": "code", "source_file": "authenticator\\src\\main\\kotlin\\com\\bitwarden\\authenticator\\data\\platform\\manager\\lock\\model\\AppLockState.kt", "source_location": "L6"}], "edges": [{"source": "authenticator_src_main_kotlin_com_bitwarden_authenticator_data_platform_manager_lock_model_applockstate_kt", "target": "applockstate_applockstate", "relation": "contains", "confidence": "EXTRACTED", "source_file": "authenticator\\src\\main\\kotlin\\com\\bitwarden\\authenticator\\data\\platform\\manager\\lock\\model\\AppLockState.kt", "source_location": "L6", "weight": 1.0}], "raw_calls": []}