{"nodes": [{"id": "app_src_main_kotlin_com_x8bit_bitwarden_data_platform_manager_model_synccipherdeletedata_kt", "label": "SyncCipherDeleteData.kt", "file_type": "code", "source_file": "app\\src\\main\\kotlin\\com\\x8bit\\bitwarden\\data\\platform\\manager\\model\\SyncCipherDeleteData.kt", "source_location": "L1"}, {"id": "synccipherdeletedata_synccipherdeletedata", "label": "SyncCipherDeleteData", "file_type": "code", "source_file": "app\\src\\main\\kotlin\\com\\x8bit\\bitwarden\\data\\platform\\manager\\model\\SyncCipherDeleteData.kt", "source_location": "L6"}], "edges": [{"source": "app_src_main_kotlin_com_x8bit_bitwarden_data_platform_manager_model_synccipherdeletedata_kt", "target": "synccipherdeletedata_synccipherdeletedata", "relation": "contains", "confidence": "EXTRACTED", "source_file": "app\\src\\main\\kotlin\\com\\x8bit\\bitwarden\\data\\platform\\manager\\model\\SyncCipherDeleteData.kt", "source_location": "L6", "weight": 1.0}], "raw_calls": []}