{"nodes": [{"id": "network_src_main_kotlin_com_bitwarden_network_model_kdftypejson_kt", "label": "KdfTypeJson.kt", "file_type": "code", "source_file": "network\\src\\main\\kotlin\\com\\bitwarden\\network\\model\\KdfTypeJson.kt", "source_location": "L1"}, {"id": "kdftypejson_kdftypejson", "label": "KdfTypeJson", "file_type": "code", "source_file": "network\\src\\main\\kotlin\\com\\bitwarden\\network\\model\\KdfTypeJson.kt", "source_location": "L11"}, {"id": "kdftypejson_kdftypeserializer", "label": "KdfTypeSerializer", "file_type": "code", "source_file": "network\\src\\main\\kotlin\\com\\bitwarden\\network\\model\\KdfTypeJson.kt", "source_location": "L20"}], "edges": [{"source": "network_src_main_kotlin_com_bitwarden_network_model_kdftypejson_kt", "target": "kdftypejson_kdftypejson", "relation": "contains", "confidence": "EXTRACTED", "source_file": "network\\src\\main\\kotlin\\com\\bitwarden\\network\\model\\KdfTypeJson.kt", "source_location": "L11", "weight": 1.0}, {"source": "network_src_main_kotlin_com_bitwarden_network_model_kdftypejson_kt", "target": "kdftypejson_kdftypeserializer", "relation": "contains", "confidence": "EXTRACTED", "source_file": "network\\src\\main\\kotlin\\com\\bitwarden\\network\\model\\KdfTypeJson.kt", "source_location": "L20", "weight": 1.0}], "raw_calls": []}