{"nodes": [{"id": "app_src_main_kotlin_com_x8bit_bitwarden_ui_vault_feature_exportitems_reviewexport_reviewexportnavigation_kt", "label": "ReviewExportNavigation.kt", "file_type": "code", "source_file": "app\\src\\main\\kotlin\\com\\x8bit\\bitwarden\\ui\\vault\\feature\\exportitems\\reviewexport\\ReviewExportNavigation.kt", "source_location": "L1"}, {"id": "reviewexportnavigation_reviewexportdestination", "label": "reviewExportDestination()", "file_type": "code", "source_file": "app\\src\\main\\kotlin\\com\\x8bit\\bitwarden\\ui\\vault\\feature\\exportitems\\reviewexport\\ReviewExportNavigation.kt", "source_location": "L32"}, {"id": "reviewexportnavigation_navigatetoreviewexport", "label": "navigateToReviewExport()", "file_type": "code", "source_file": "app\\src\\main\\kotlin\\com\\x8bit\\bitwarden\\ui\\vault\\feature\\exportitems\\reviewexport\\ReviewExportNavigation.kt", "source_location": "L51"}], "edges": [{"source": "app_src_main_kotlin_com_x8bit_bitwarden_ui_vault_feature_exportitems_reviewexport_reviewexportnavigation_kt", "target": "reviewexportnavigation_reviewexportdestination", "relation": "contains", "confidence": "EXTRACTED", "source_file": "app\\src\\main\\kotlin\\com\\x8bit\\bitwarden\\ui\\vault\\feature\\exportitems\\reviewexport\\ReviewExportNavigation.kt", "source_location": "L32", "weight": 1.0}, {"source": "app_src_main_kotlin_com_x8bit_bitwarden_ui_vault_feature_exportitems_reviewexport_reviewexportnavigation_kt", "target": "reviewexportnavigation_navigatetoreviewexport", "relation": "contains", "confidence": "EXTRACTED", "source_file": "app\\src\\main\\kotlin\\com\\x8bit\\bitwarden\\ui\\vault\\feature\\exportitems\\reviewexport\\ReviewExportNavigation.kt", "source_location": "L51", "weight": 1.0}], "raw_calls": []}