{"nodes": [{"id": "app_src_main_kotlin_com_x8bit_bitwarden_data_vault_datasource_disk_database_vaultdatabase_kt", "label": "VaultDatabase.kt", "file_type": "code", "source_file": "app\\src\\main\\kotlin\\com\\x8bit\\bitwarden\\data\\vault\\datasource\\disk\\database\\VaultDatabase.kt", "source_location": "L1"}, {"id": "vaultdatabase_vaultdatabase", "label": "VaultDatabase", "file_type": "code", "source_file": "app\\src\\main\\kotlin\\com\\x8bit\\bitwarden\\data\\vault\\datasource\\disk\\database\\VaultDatabase.kt", "source_location": "L22"}, {"id": "vaultdatabase_vaultdatabase_cipherdao", "label": ".cipherDao()", "file_type": "code", "source_file": "app\\src\\main\\kotlin\\com\\x8bit\\bitwarden\\data\\vault\\datasource\\disk\\database\\VaultDatabase.kt", "source_location": "L43"}, {"id": "vaultdatabase_vaultdatabase_collectiondao", "label": ".collectionDao()", "file_type": "code", "source_file": "app\\src\\main\\kotlin\\com\\x8bit\\bitwarden\\data\\vault\\datasource\\disk\\database\\VaultDatabase.kt", "source_location": "L48"}, {"id": "vaultdatabase_vaultdatabase_domainsdao", "label": ".domainsDao()", "file_type": "code", "source_file": "app\\src\\main\\kotlin\\com\\x8bit\\bitwarden\\data\\vault\\datasource\\disk\\database\\VaultDatabase.kt", "source_location": "L53"}, {"id": "vaultdatabase_vaultdatabase_folderdao", "label": ".folderDao()", "file_type": "code", "source_file": "app\\src\\main\\kotlin\\com\\x8bit\\bitwarden\\data\\vault\\datasource\\disk\\database\\VaultDatabase.kt", "source_location": "L58"}, {"id": "vaultdatabase_vaultdatabase_sendsdao", "label": ".sendsDao()", "file_type": "code", "source_file": "app\\src\\main\\kotlin\\com\\x8bit\\bitwarden\\data\\vault\\datasource\\disk\\database\\VaultDatabase.kt", "source_location": "L63"}], "edges": [{"source": "app_src_main_kotlin_com_x8bit_bitwarden_data_vault_datasource_disk_database_vaultdatabase_kt", "target": "vaultdatabase_vaultdatabase", "relation": "contains", "confidence": "EXTRACTED", "source_file": "app\\src\\main\\kotlin\\com\\x8bit\\bitwarden\\data\\vault\\datasource\\disk\\database\\VaultDatabase.kt", "source_location": "L22", "weight": 1.0}, {"source": "vaultdatabase_vaultdatabase", "target": "vaultdatabase_vaultdatabase_cipherdao", "relation": "method", "confidence": "EXTRACTED", "source_file": "app\\src\\main\\kotlin\\com\\x8bit\\bitwarden\\data\\vault\\datasource\\disk\\database\\VaultDatabase.kt", "source_location": "L43", "weight": 1.0}, {"source": "vaultdatabase_vaultdatabase", "target": "vaultdatabase_vaultdatabase_collectiondao", "relation": "method", "confidence": "EXTRACTED", "source_file": "app\\src\\main\\kotlin\\com\\x8bit\\bitwarden\\data\\vault\\datasource\\disk\\database\\VaultDatabase.kt", "source_location": "L48", "weight": 1.0}, {"source": "vaultdatabase_vaultdatabase", "target": "vaultdatabase_vaultdatabase_domainsdao", "relation": "method", "confidence": "EXTRACTED", "source_file": "app\\src\\main\\kotlin\\com\\x8bit\\bitwarden\\data\\vault\\datasource\\disk\\database\\VaultDatabase.kt", "source_location": "L53", "weight": 1.0}, {"source": "vaultdatabase_vaultdatabase", "target": "vaultdatabase_vaultdatabase_folderdao", "relation": "method", "confidence": "EXTRACTED", "source_file": "app\\src\\main\\kotlin\\com\\x8bit\\bitwarden\\data\\vault\\datasource\\disk\\database\\VaultDatabase.kt", "source_location": "L58", "weight": 1.0}, {"source": "vaultdatabase_vaultdatabase", "target": "vaultdatabase_vaultdatabase_sendsdao", "relation": "method", "confidence": "EXTRACTED", "source_file": "app\\src\\main\\kotlin\\com\\x8bit\\bitwarden\\data\\vault\\datasource\\disk\\database\\VaultDatabase.kt", "source_location": "L63", "weight": 1.0}], "raw_calls": []}