{"nodes": [{"id": "core_src_main_kotlin_com_bitwarden_core_data_util_inputstreamextensions_kt", "label": "InputStreamExtensions.kt", "file_type": "code", "source_file": "core\\src\\main\\kotlin\\com\\bitwarden\\core\\data\\util\\InputStreamExtensions.kt", "source_location": "L1"}, {"id": "inputstreamextensions_sdkagnostictransferto", "label": "sdkAgnosticTransferTo()", "file_type": "code", "source_file": "core\\src\\main\\kotlin\\com\\bitwarden\\core\\data\\util\\InputStreamExtensions.kt", "source_location": "L34"}], "edges": [{"source": "core_src_main_kotlin_com_bitwarden_core_data_util_inputstreamextensions_kt", "target": "inputstreamextensions_sdkagnostictransferto", "relation": "contains", "confidence": "EXTRACTED", "source_file": "core\\src\\main\\kotlin\\com\\bitwarden\\core\\data\\util\\InputStreamExtensions.kt", "source_location": "L34", "weight": 1.0}], "raw_calls": []}