{"nodes": [{"id": "app_src_main_kotlin_com_x8bit_bitwarden_data_auth_repository_di_authrepositorymodule_kt", "label": "AuthRepositoryModule.kt", "file_type": "code", "source_file": "app\\src\\main\\kotlin\\com\\x8bit\\bitwarden\\data\\auth\\repository\\di\\AuthRepositoryModule.kt", "source_location": "L1"}, {"id": "authrepositorymodule_authrepositorymodule", "label": "AuthRepositoryModule", "file_type": "code", "source_file": "app\\src\\main\\kotlin\\com\\x8bit\\bitwarden\\data\\auth\\repository\\di\\AuthRepositoryModule.kt", "source_location": "L44"}, {"id": "authrepositorymodule_authrepositorymodule_providesauthrepository", "label": ".providesAuthRepository()", "file_type": "code", "source_file": "app\\src\\main\\kotlin\\com\\x8bit\\bitwarden\\data\\auth\\repository\\di\\AuthRepositoryModule.kt", "source_location": "L48"}, {"id": "authrepositorymodule_authrepositorymodule_providesuserstatemanager", "label": ".providesUserStateManager()", "file_type": "code", "source_file": "app\\src\\main\\kotlin\\com\\x8bit\\bitwarden\\data\\auth\\repository\\di\\AuthRepositoryModule.kt", "source_location": "L108"}], "edges": [{"source": "app_src_main_kotlin_com_x8bit_bitwarden_data_auth_repository_di_authrepositorymodule_kt", "target": "authrepositorymodule_authrepositorymodule", "relation": "contains", "confidence": "EXTRACTED", "source_file": "app\\src\\main\\kotlin\\com\\x8bit\\bitwarden\\data\\auth\\repository\\di\\AuthRepositoryModule.kt", "source_location": "L44", "weight": 1.0}, {"source": "authrepositorymodule_authrepositorymodule", "target": "authrepositorymodule_authrepositorymodule_providesauthrepository", "relation": "method", "confidence": "EXTRACTED", "source_file": "app\\src\\main\\kotlin\\com\\x8bit\\bitwarden\\data\\auth\\repository\\di\\AuthRepositoryModule.kt", "source_location": "L48", "weight": 1.0}, {"source": "authrepositorymodule_authrepositorymodule", "target": "authrepositorymodule_authrepositorymodule_providesuserstatemanager", "relation": "method", "confidence": "EXTRACTED", "source_file": "app\\src\\main\\kotlin\\com\\x8bit\\bitwarden\\data\\auth\\repository\\di\\AuthRepositoryModule.kt", "source_location": "L108", "weight": 1.0}], "raw_calls": []}