{"nodes": [{"id": "app_src_main_kotlin_com_x8bit_bitwarden_ui_auth_feature_enterprisesignon_enterprisesignonscreen_kt", "label": "EnterpriseSignOnScreen.kt", "file_type": "code", "source_file": "app\\src\\main\\kotlin\\com\\x8bit\\bitwarden\\ui\\auth\\feature\\enterprisesignon\\EnterpriseSignOnScreen.kt", "source_location": "L1"}, {"id": "enterprisesignonscreen_enterprisesignonscreen", "label": "EnterpriseSignOnScreen()", "file_type": "code", "source_file": "app\\src\\main\\kotlin\\com\\x8bit\\bitwarden\\ui\\auth\\feature\\enterprisesignon\\EnterpriseSignOnScreen.kt", "source_location": "L49"}], "edges": [{"source": "app_src_main_kotlin_com_x8bit_bitwarden_ui_auth_feature_enterprisesignon_enterprisesignonscreen_kt", "target": "enterprisesignonscreen_enterprisesignonscreen", "relation": "contains", "confidence": "EXTRACTED", "source_file": "app\\src\\main\\kotlin\\com\\x8bit\\bitwarden\\ui\\auth\\feature\\enterprisesignon\\EnterpriseSignOnScreen.kt", "source_location": "L49", "weight": 1.0}], "raw_calls": []}