{"nodes": [{"id": "authenticator_src_main_kotlin_com_bitwarden_authenticator_data_platform_manager_crashlogsmanager_kt", "label": "CrashLogsManager.kt", "file_type": "code", "source_file": "authenticator\\src\\main\\kotlin\\com\\bitwarden\\authenticator\\data\\platform\\manager\\CrashLogsManager.kt", "source_location": "L1"}, {"id": "crashlogsmanager_crashlogsmanager", "label": "CrashLogsManager", "file_type": "code", "source_file": "authenticator\\src\\main\\kotlin\\com\\bitwarden\\authenticator\\data\\platform\\manager\\CrashLogsManager.kt", "source_location": "L7"}], "edges": [{"source": "authenticator_src_main_kotlin_com_bitwarden_authenticator_data_platform_manager_crashlogsmanager_kt", "target": "crashlogsmanager_crashlogsmanager", "relation": "contains", "confidence": "EXTRACTED", "source_file": "authenticator\\src\\main\\kotlin\\com\\bitwarden\\authenticator\\data\\platform\\manager\\CrashLogsManager.kt", "source_location": "L7", "weight": 1.0}], "raw_calls": []}