{"nodes": [{"id": "core_src_main_kotlin_com_bitwarden_core_data_serializer_instantserializer_kt", "label": "InstantSerializer.kt", "file_type": "code", "source_file": "core\\src\\main\\kotlin\\com\\bitwarden\\core\\data\\serializer\\InstantSerializer.kt", "source_location": "L1"}, {"id": "instantserializer_instantserializer", "label": "InstantSerializer", "file_type": "code", "source_file": "core\\src\\main\\kotlin\\com\\bitwarden\\core\\data\\serializer\\InstantSerializer.kt", "source_location": "L17"}, {"id": "instantserializer_instantserializer_deserialize", "label": ".deserialize()", "file_type": "code", "source_file": "core\\src\\main\\kotlin\\com\\bitwarden\\core\\data\\serializer\\InstantSerializer.kt", "source_location": "L28"}, {"id": "instantserializer_instantserializer_serialize", "label": ".serialize()", "file_type": "code", "source_file": "core\\src\\main\\kotlin\\com\\bitwarden\\core\\data\\serializer\\InstantSerializer.kt", "source_location": "L33"}], "edges": [{"source": "core_src_main_kotlin_com_bitwarden_core_data_serializer_instantserializer_kt", "target": "instantserializer_instantserializer", "relation": "contains", "confidence": "EXTRACTED", "source_file": "core\\src\\main\\kotlin\\com\\bitwarden\\core\\data\\serializer\\InstantSerializer.kt", "source_location": "L17", "weight": 1.0}, {"source": "instantserializer_instantserializer", "target": "instantserializer_instantserializer_deserialize", "relation": "method", "confidence": "EXTRACTED", "source_file": "core\\src\\main\\kotlin\\com\\bitwarden\\core\\data\\serializer\\InstantSerializer.kt", "source_location": "L28", "weight": 1.0}, {"source": "instantserializer_instantserializer", "target": "instantserializer_instantserializer_serialize", "relation": "method", "confidence": "EXTRACTED", "source_file": "core\\src\\main\\kotlin\\com\\bitwarden\\core\\data\\serializer\\InstantSerializer.kt", "source_location": "L33", "weight": 1.0}], "raw_calls": []}