{"nodes": [{"id": "network_src_main_kotlin_com_bitwarden_network_service_syncserviceimpl_kt", "label": "SyncServiceImpl.kt", "file_type": "code", "source_file": "network\\src\\main\\kotlin\\com\\bitwarden\\network\\service\\SyncServiceImpl.kt", "source_location": "L1"}, {"id": "syncserviceimpl_syncserviceimpl", "label": "SyncServiceImpl", "file_type": "code", "source_file": "network\\src\\main\\kotlin\\com\\bitwarden\\network\\service\\SyncServiceImpl.kt", "source_location": "L7"}, {"id": "syncserviceimpl_syncserviceimpl_sync", "label": ".sync()", "file_type": "code", "source_file": "network\\src\\main\\kotlin\\com\\bitwarden\\network\\service\\SyncServiceImpl.kt", "source_location": "L10"}, {"id": "syncserviceimpl_syncserviceimpl_getaccountrevisiondatemillis", "label": ".getAccountRevisionDateMillis()", "file_type": "code", "source_file": "network\\src\\main\\kotlin\\com\\bitwarden\\network\\service\\SyncServiceImpl.kt", "source_location": "L14"}], "edges": [{"source": "network_src_main_kotlin_com_bitwarden_network_service_syncserviceimpl_kt", "target": "syncserviceimpl_syncserviceimpl", "relation": "contains", "confidence": "EXTRACTED", "source_file": "network\\src\\main\\kotlin\\com\\bitwarden\\network\\service\\SyncServiceImpl.kt", "source_location": "L7", "weight": 1.0}, {"source": "syncserviceimpl_syncserviceimpl", "target": "syncserviceimpl_syncserviceimpl_sync", "relation": "method", "confidence": "EXTRACTED", "source_file": "network\\src\\main\\kotlin\\com\\bitwarden\\network\\service\\SyncServiceImpl.kt", "source_location": "L10", "weight": 1.0}, {"source": "syncserviceimpl_syncserviceimpl", "target": "syncserviceimpl_syncserviceimpl_getaccountrevisiondatemillis", "relation": "method", "confidence": "EXTRACTED", "source_file": "network\\src\\main\\kotlin\\com\\bitwarden\\network\\service\\SyncServiceImpl.kt", "source_location": "L14", "weight": 1.0}], "raw_calls": []}