{"nodes": [{"id": "core_src_test_kotlin_com_bitwarden_core_data_manager_toast_toastmanagertest_kt", "label": "ToastManagerTest.kt", "file_type": "code", "source_file": "core\\src\\test\\kotlin\\com\\bitwarden\\core\\data\\manager\\toast\\ToastManagerTest.kt", "source_location": "L1"}, {"id": "toastmanagertest_toastmanagertest", "label": "ToastManagerTest", "file_type": "code", "source_file": "core\\src\\test\\kotlin\\com\\bitwarden\\core\\data\\manager\\toast\\ToastManagerTest.kt", "source_location": "L16"}, {"id": "toastmanagertest_toastmanagertest_setup", "label": ".setup()", "file_type": "code", "source_file": "core\\src\\test\\kotlin\\com\\bitwarden\\core\\data\\manager\\toast\\ToastManagerTest.kt", "source_location": "L25"}, {"id": "toastmanagertest_toastmanagertest_teardown", "label": ".tearDown()", "file_type": "code", "source_file": "core\\src\\test\\kotlin\\com\\bitwarden\\core\\data\\manager\\toast\\ToastManagerTest.kt", "source_location": "L32"}, {"id": "toastmanagertest_toastmanagertest_show_with_string_should_call_show_on_toast", "label": ".`show with string should call show on Toast`()", "file_type": "code", "source_file": "core\\src\\test\\kotlin\\com\\bitwarden\\core\\data\\manager\\toast\\ToastManagerTest.kt", "source_location": "L37"}, {"id": "toastmanagertest_toastmanagertest_show_with_string_resource_should_call_show_on_toast", "label": ".`show with string resource should call show on Toast`()", "file_type": "code", "source_file": "core\\src\\test\\kotlin\\com\\bitwarden\\core\\data\\manager\\toast\\ToastManagerTest.kt", "source_location": "L53"}], "edges": [{"source": "core_src_test_kotlin_com_bitwarden_core_data_manager_toast_toastmanagertest_kt", "target": "toastmanagertest_toastmanagertest", "relation": "contains", "confidence": "EXTRACTED", "source_file": "core\\src\\test\\kotlin\\com\\bitwarden\\core\\data\\manager\\toast\\ToastManagerTest.kt", "source_location": "L16", "weight": 1.0}, {"source": "toastmanagertest_toastmanagertest", "target": "toastmanagertest_toastmanagertest_setup", "relation": "method", "confidence": "EXTRACTED", "source_file": "core\\src\\test\\kotlin\\com\\bitwarden\\core\\data\\manager\\toast\\ToastManagerTest.kt", "source_location": "L25", "weight": 1.0}, {"source": "toastmanagertest_toastmanagertest", "target": "toastmanagertest_toastmanagertest_teardown", "relation": "method", "confidence": "EXTRACTED", "source_file": "core\\src\\test\\kotlin\\com\\bitwarden\\core\\data\\manager\\toast\\ToastManagerTest.kt", "source_location": "L32", "weight": 1.0}, {"source": "toastmanagertest_toastmanagertest", "target": "toastmanagertest_toastmanagertest_show_with_string_should_call_show_on_toast", "relation": "method", "confidence": "EXTRACTED", "source_file": "core\\src\\test\\kotlin\\com\\bitwarden\\core\\data\\manager\\toast\\ToastManagerTest.kt", "source_location": "L37", "weight": 1.0}, {"source": "toastmanagertest_toastmanagertest", "target": "toastmanagertest_toastmanagertest_show_with_string_resource_should_call_show_on_toast", "relation": "method", "confidence": "EXTRACTED", "source_file": "core\\src\\test\\kotlin\\com\\bitwarden\\core\\data\\manager\\toast\\ToastManagerTest.kt", "source_location": "L53", "weight": 1.0}], "raw_calls": []}